.DS_Store
.gitignore
.gitmodules
INSTALL.txt
MANIFEST.in
README.md
RELEASE_NOTES.txt
cAction.so
dirac.so
epydoc.cfg
fix_develop_install.py
setup.py
soundtouch.so
welcome.rtf
examples/.DS_Store
examples/afromb/afromb.py
examples/cowbell/cowbell.py
examples/cowbell/sounds/cowbell0.wav
examples/cowbell/sounds/cowbell1.wav
examples/cowbell/sounds/cowbell2.wav
examples/cowbell/sounds/cowbell3.wav
examples/cowbell/sounds/cowbell4.wav
examples/cowbell/sounds/trill.wav
examples/cowbell/sounds/walken0.wav
examples/cowbell/sounds/walken1.wav
examples/cowbell/sounds/walken10.wav
examples/cowbell/sounds/walken11.wav
examples/cowbell/sounds/walken12.wav
examples/cowbell/sounds/walken13.wav
examples/cowbell/sounds/walken14.wav
examples/cowbell/sounds/walken15.wav
examples/cowbell/sounds/walken2.wav
examples/cowbell/sounds/walken3.wav
examples/cowbell/sounds/walken4.wav
examples/cowbell/sounds/walken5.wav
examples/cowbell/sounds/walken6.wav
examples/cowbell/sounds/walken7.wav
examples/cowbell/sounds/walken8.wav
examples/cowbell/sounds/walken9.wav
examples/earworm/README.txt
examples/earworm/earworm.py
examples/earworm/earworm_support.py
examples/earworm/utils.py
examples/filter/filter.py
examples/limp/lopside.py
examples/music/.DS_Store
examples/music/Hiiragi_Fukuda-Open_Fields_Blues.mp3
examples/music/Karl_Blau-Gnos_Levohs.mp3
examples/music/Raleigh_Moncrief-Guppies.mp3
examples/music/Tracky_Birthday-Newish_Disco.mp3
examples/music/attribution.txt
examples/one/one.py
examples/quanta/quanta.py
examples/reverse/reverse.py
examples/save/save.py
examples/selection/tonic.py
examples/sorting/sorting.py
examples/sorting/sorting_pitch.py
examples/sorting/sorting_timbre.py
examples/step/step-by-pitch.py
examples/step/step-by-section.py
examples/step/step.py
examples/stretch/beatshift.py
examples/stretch/cycle_dirac.py
examples/stretch/cycle_soundtouch.py
examples/stretch/simple_stretch.py
examples/swinger/swinger.py
examples/videx/vafroma.py
examples/videx/vafroma2.py
remix.egg-info/PKG-INFO
remix.egg-info/SOURCES.txt
remix.egg-info/dependency_links.txt
remix.egg-info/top_level.txt
