Metadata-Version: 1.1
Name: remix
Version: 2.4.0
Summary: The internet synthesizer. Make things with music.
Home-page: http://developer.echonest.com/
Author: Brian Whitman
Author-email: brian@echonest.com
License: New BSD
Platform: UNKNOWN
Requires: os
Requires: urllib
Requires: httplib
Requires: mimetypes
Requires: tempfile
Requires: commands
Requires: struct
Requires: wave
Requires: numpy
Requires: Numeric
